{"route_long_name": "Pelham Pkwy - Fordham Rd", "route_color": "006CB7", "route_id": "BX12+", "route_url": "http://web.mta.info/nyct/bus/schedule/bronx/bx012scur.pdf", "directions": {"0": {"shapes": [[["SBS120131", 54.73], ["SBS120114", 41.07], ["SBS120103", 4.19]], [["SBS120131", 65.02], ["SBS120114", 33.63], ["SBS120103", 1.33]], [["SBS120131", 55.08], ["SBS120114", 25.62], ["SBS120103", 19.29]], [["SBS120131", 65.66], ["SBS120114", 33.69], ["SBS120103", 0.63]], [["SBS120131", 52.85], ["SBS120114", 32.65], ["SBS120132", 9.73], ["SBS120115", 2.69], ["SBS120103", 1.95], ["SBS120084", 0.1]]], "headsign": "SELECT BUS SERVICE BAY PLAZA CO-OP CITY"}, "1": {"shapes": [[["SBS120133", 51.59], ["SBS120127", 41.41], ["SBS120128", 4.88], ["SBS120125", 2.1]], [["SBS120133", 63.14], ["SBS120127", 35.4], ["SBS120128", 1.45]], [["SBS120133", 54.64], ["SBS120127", 25.98], ["SBS120128", 19.36]], [["SBS120133", 64.57], ["SBS120127", 34.59], ["SBS120128", 0.82]], [["SBS120125", 59.06], ["SBS120133", 24.97], ["SBS120127", 15.05], ["SBS120128", 0.9]]], "headsign": "SELECT BUS SERVICE BROADWAY INWOOD"}}, "route_short_name": "Bx12-SBS"}